cd_benchmark/__init__.py
cd_benchmark/analysis.py
cd_benchmark/benchmark.py
cd_benchmark/generator.py
cd_benchmark/globals.py
cd_benchmark/imports.py
cd_benchmark/network.py
cd_benchmark/statistics.py
cd_benchmark/support.py
cd_benchmark/visualization.py
cd_benchmark-0.1.1.dist-info/METADATA
cd_benchmark-0.1.1.dist-info/WHEEL
cd_benchmark-0.1.1.dist-info/licenses/LICENSE
cd_benchmark-0.1.1.dist-info/RECORD
