Metadata-Version: 2.4
Name: cd-benchmark
Version: 0.1.1
Summary: Community Detection Benchmark: NetworkX/igraph/CDlib
Project-URL: Homepage, https://github.com/rpritr/network-community-detection-benchmark
Project-URL: Issues, https://github.com/rpritr/network-community-detection-benchmark/issues
Author-email: Robi Pritržnik <robi@steerscape.com>
License: MIT
License-File: LICENSE
Keywords: benchmark,cdlib,community detection,graph,igraph,networks,networkx
Classifier: Intended Audience :: Science/Research
Classifier: License :: OSI Approved :: MIT License
Classifier: Programming Language :: Python :: 3
Classifier: Topic :: Scientific/Engineering :: Information Analysis
Requires-Python: >=3.9
Requires-Dist: cdlib>=0.3.0
Requires-Dist: igraph>=0.11.0
Requires-Dist: leidenalg>=0.10.0
Requires-Dist: networkx>=2.8
Requires-Dist: numpy>=1.23
Requires-Dist: pandas>=1.5
Requires-Dist: python-igraph>=0.10
Provides-Extra: viz
Requires-Dist: matplotlib>=3.6; extra == 'viz'
Requires-Dist: pyvis>=0.3.2; extra == 'viz'
